youtube_extractor/__init__.py
youtube_extractor/youtube_video_id_extractor.py
youtube_extractor-0.1.0.dist-info/LICENSE
youtube_extractor-0.1.0.dist-info/METADATA
youtube_extractor-0.1.0.dist-info/WHEEL
youtube_extractor-0.1.0.dist-info/top_level.txt
youtube_extractor-0.1.0.dist-info/RECORD
