Metadata-Version: 2.1
Name: youtube-extractor
Version: 0.1.0
Summary: A package for extracting YouTube video IDs from URLs
Home-page: https://github.com/super-nived/youtube-extractor
Author: super nived
Author-email: nivedchandran7@gmail.com
License: MIT
Classifier: License :: OSI Approved :: MIT License
Classifier: Programming Language :: Python :: 3
Classifier: Programming Language :: Python :: 3.6
Classifier: Programming Language :: Python :: 3.7
Classifier: Programming Language :: Python :: 3.8
License-File: LICENSE
Requires-Dist: requests
